puller/__init__.py
puller/config/__init__.py
ams_puller-0.5.0.dist-info/LICENSE
ams_puller-0.5.0.dist-info/METADATA
ams_puller-0.5.0.dist-info/WHEEL
ams_puller-0.5.0.dist-info/entry_points.txt
ams_puller-0.5.0.dist-info/top_level.txt
ams_puller-0.5.0.dist-info/RECORD
