Metadata-Version: 2.1
Name: ams-puller
Version: 0.5.0
Summary: An automatic repo puller
Home-page: https://github.com/adesso-mobile/puller
Author: adesso mobile solutions GmbH
Author-email: it-operations@adesso-mobile.de
License: UNKNOWN
Project-URL: Bug Tracker, https://github.com/adesso-mobile/puller
Platform: UNKNOWN
Classifier: Programming Language :: Python :: 3
Classifier: License :: OSI Approved :: MIT License
Classifier: Operating System :: OS Independent
Requires-Python: >=3.6
License-File: LICENSE
Requires-Dist: fastapi
Requires-Dist: pyyaml
Requires-Dist: uvicorn
Requires-Dist: shellescape
